README.txt
setup.py
docs/HISTORY.txt
z3c/__init__.py
z3c.discriminator.egg-info/PKG-INFO
z3c.discriminator.egg-info/SOURCES.txt
z3c.discriminator.egg-info/dependency_links.txt
z3c.discriminator.egg-info/entry_points.txt
z3c.discriminator.egg-info/namespace_packages.txt
z3c.discriminator.egg-info/not-zip-safe
z3c.discriminator.egg-info/requires.txt
z3c.discriminator.egg-info/top_level.txt
z3c/discriminator/README.txt
z3c/discriminator/__init__.py
z3c/discriminator/discriminator.py
z3c/discriminator/patches.py
z3c/discriminator/tests.py
