Metadata-Version: 1.0
Name: z3c.discriminator
Version: 0.2
Summary: Provides a formalism for marking adapter specifications as discriminators.
Home-page: UNKNOWN
Author: Malthe Borch
Author-email: mborch@gmail.com
License: ZPL
Keywords: zope adapter discriminator
Platform: UNKNOWN
Classifier: Framework :: Zope2
Classifier: Framework :: Zope3
Classifier: Programming Language :: Python
Classifier: Topic :: Software Development :: Libraries :: Python Modules
